[
  {
    "reservation": [
      {
        "id": "3690b2b9-ed13-4bb8-a8e2-62d6bfc71bce",
        "table_number": 5309,
        "reservation_time": "2023-08-03T22:14:45.857Z",
        "created_at": "2023-08-04T03:24:36.942Z",
        "updated_at": "2023-08-03T18:20:14.737Z",
        "guest_id": "user_entity_pk",
        "restaurant_id": "main_entity_pk"
      },
      {
        "id": "cf2f4702-55b9-4ec7-96cb-1be0417a39d8",
        "table_number": 15300,
        "reservation_time": "2023-08-04T00:06:53.134Z",
        "created_at": "2023-08-03T16:38:04.448Z",
        "updated_at": "2023-08-03T18:27:00.264Z",
        "guest_id": "user_entity_pk",
        "restaurant_id": "main_entity_pk"
      },
      {
        "id": "5be81876-58b7-4242-ad51-c048fb14924d",
        "table_number": 93478,
        "reservation_time": "2023-08-03T21:06:20.151Z",
        "created_at": "2023-08-03T18:47:30.937Z",
        "updated_at": "2023-08-04T07:10:07.387Z",
        "guest_id": "user_entity_pk",
        "restaurant_id": "main_entity_pk"
      },
      {
        "id": "629a9b53-626c-4d64-a3b7-dde965eeee00",
        "table_number": 75540,
        "reservation_time": "2023-08-04T10:28:01.287Z",
        "created_at": "2023-08-03T23:25:59.450Z",
        "updated_at": "2023-08-04T06:57:53.238Z",
        "guest_id": "user_entity_pk",
        "restaurant_id": "main_entity_pk"
      },
      {
        "id": "62875d26-a22f-499f-bf30-8bb6c1779c83",
        "table_number": 37341,
        "reservation_time": "2023-08-03T20:12:41.374Z",
        "created_at": "2023-08-04T09:01:45.954Z",
        "updated_at": "2023-08-03T19:52:35.495Z",
        "guest_id": "user_entity_pk",
        "restaurant_id": "main_entity_pk"
      }
    ],
    "menu": [
      {
        "id": "792f6548-9ed6-4e2f-bce9-57f22744806e",
        "name": "Breakfast Specials",
        "created_at": "2023-08-04T10:40:19.268Z",
        "updated_at": "2023-08-03T23:52:58.366Z",
        "restaurant_id": "main_entity_pk"
      },
      {
        "id": "e1da8be1-a3d6-4025-ae6e-0398fa8c4faf",
        "name": "Chef's Recommendations",
        "created_at": "2023-08-04T02:19:01.048Z",
        "updated_at": "2023-08-03T18:15:11.916Z",
        "restaurant_id": "main_entity_pk"
      },
      {
        "id": "cd043487-72ca-4cbc-a59f-1cb156fd3d3b",
        "name": "Vegetarian Delights",
        "created_at": "2023-08-03T14:33:11.700Z",
        "updated_at": "2023-08-04T00:00:45.789Z",
        "restaurant_id": "main_entity_pk"
      },
      {
        "id": "730d83c1-2f1b-42e5-966d-d91821fc0887",
        "name": "Seafood Extravaganza",
        "created_at": "2023-08-03T13:52:26.499Z",
        "updated_at": "2023-08-04T02:06:12.873Z",
        "restaurant_id": "main_entity_pk"
      },
      {
        "id": "004654c6-9f5a-4de5-9d5d-880fb045df69",
        "name": "Sweet Treats",
        "created_at": "2023-08-04T06:19:27.240Z",
        "updated_at": "2023-08-04T09:18:23.558Z",
        "restaurant_id": "main_entity_pk"
      }
    ]
  },
  {
    "reservation": [
      {
        "id": "4352dc7e-fad0-4061-b118-99af3274a2cf",
        "table_number": 71697,
        "reservation_time": "2023-08-03T18:59:57.657Z",
        "created_at": "2023-08-04T09:08:49.170Z",
        "updated_at": "2023-08-03T19:17:37.877Z",
        "guest_id": "user_entity_pk",
        "restaurant_id": "main_entity_pk"
      },
      {
        "id": "fd83ad85-f5ef-449d-9eb3-b74a90ac360c",
        "table_number": 44487,
        "reservation_time": "2023-08-04T02:35:06.890Z",
        "created_at": "2023-08-03T14:45:53.882Z",
        "updated_at": "2023-08-03T13:41:59.054Z",
        "guest_id": "user_entity_pk",
        "restaurant_id": "main_entity_pk"
      },
      {
        "id": "3001b81e-13c0-4d91-9b61-2d7b01249cdd",
        "table_number": 50486,
        "reservation_time": "2023-08-03T22:33:31.357Z",
        "created_at": "2023-08-04T11:09:05.381Z",
        "updated_at": "2023-08-04T09:14:24.898Z",
        "guest_id": "user_entity_pk",
        "restaurant_id": "main_entity_pk"
      },
      {
        "id": "8ac796d1-2ecc-4618-bc57-a04f0b507c15",
        "table_number": 28316,
        "reservation_time": "2023-08-03T15:10:44.480Z",
        "created_at": "2023-08-03T12:57:57.719Z",
        "updated_at": "2023-08-04T03:57:59.594Z",
        "guest_id": "user_entity_pk",
        "restaurant_id": "main_entity_pk"
      },
      {
        "id": "6650e472-1a58-4db0-87d2-578bc9888e2d",
        "table_number": 15030,
        "reservation_time": "2023-08-03T23:53:46.356Z",
        "created_at": "2023-08-03T22:50:50.361Z",
        "updated_at": "2023-08-04T00:07:16.405Z",
        "guest_id": "user_entity_pk",
        "restaurant_id": "main_entity_pk"
      }
    ],
    "menu": [
      {
        "id": "bceea4ae-3465-4af8-9da4-77030fa351ec",
        "name": "Breakfast Specials",
        "created_at": "2023-08-04T10:56:58.438Z",
        "updated_at": "2023-08-03T22:15:06.452Z",
        "restaurant_id": "main_entity_pk"
      },
      {
        "id": "aca35fac-dd0f-4948-98d1-76d80845dbc6",
        "name": "Lunch Combos",
        "created_at": "2023-08-03T20:37:02.725Z",
        "updated_at": "2023-08-03T22:00:02.607Z",
        "restaurant_id": "main_entity_pk"
      },
      {
        "id": "327789d5-0327-4a82-86a9-e27e7b986ae9",
        "name": "Dinner Delights",
        "created_at": "2023-08-04T08:17:55.970Z",
        "updated_at": "2023-08-04T11:59:40.668Z",
        "restaurant_id": "main_entity_pk"
      },
      {
        "id": "e723f892-7496-48dc-8f4d-d8cd51b03cad",
        "name": "Vegetarian Options",
        "created_at": "2023-08-03T19:43:30.008Z",
        "updated_at": "2023-08-03T22:49:34.072Z",
        "restaurant_id": "main_entity_pk"
      },
      {
        "id": "d5fb1052-68ca-4ee4-ba22-338aace195f5",
        "name": "Chef's Recommendations",
        "created_at": "2023-08-04T08:40:36.809Z",
        "updated_at": "2023-08-03T22:17:41.773Z",
        "restaurant_id": "main_entity_pk"
      }
    ]
  },
  {
    "reservation": [
      {
        "id": "75389952-29af-466c-9c49-7acbb5b9b46a",
        "table_number": 70956,
        "reservation_time": "2023-08-03T20:07:42.965Z",
        "created_at": "2023-08-04T07:04:45.401Z",
        "updated_at": "2023-08-04T10:14:55.481Z",
        "guest_id": "user_entity_pk",
        "restaurant_id": "main_entity_pk"
      },
      {
        "id": "f09ff523-ecfa-486e-b359-0a7ae5440a92",
        "table_number": 4721,
        "reservation_time": "2023-08-04T05:55:16.724Z",
        "created_at": "2023-08-04T00:24:14.803Z",
        "updated_at": "2023-08-03T18:27:57.123Z",
        "guest_id": "user_entity_pk",
        "restaurant_id": "main_entity_pk"
      },
      {
        "id": "eff88fc8-e0d7-4f0d-9b88-fde306390da7",
        "table_number": 85852,
        "reservation_time": "2023-08-03T16:50:18.424Z",
        "created_at": "2023-08-03T21:38:27.718Z",
        "updated_at": "2023-08-03T21:36:12.579Z",
        "guest_id": "user_entity_pk",
        "restaurant_id": "main_entity_pk"
      },
      {
        "id": "077659b1-3d9d-42c3-8011-e6452a4a1ab7",
        "table_number": 36810,
        "reservation_time": "2023-08-03T23:20:06.897Z",
        "created_at": "2023-08-04T11:37:05.532Z",
        "updated_at": "2023-08-04T00:29:25.597Z",
        "guest_id": "user_entity_pk",
        "restaurant_id": "main_entity_pk"
      },
      {
        "id": "845b8fdd-d6c6-4020-82bc-1e1b09e25dbd",
        "table_number": 85377,
        "reservation_time": "2023-08-03T15:35:39.745Z",
        "created_at": "2023-08-03T18:56:34.701Z",
        "updated_at": "2023-08-04T00:49:12.666Z",
        "guest_id": "user_entity_pk",
        "restaurant_id": "main_entity_pk"
      }
    ],
    "menu": [
      {
        "id": "1002c0eb-0405-4b32-b737-56ad5d3f6ef0",
        "name": "Grilled Salmon",
        "created_at": "2023-08-04T05:39:28.627Z",
        "updated_at": "2023-08-03T14:10:17.940Z",
        "restaurant_id": "main_entity_pk"
      },
      {
        "id": "a1c7fc72-16e7-42f2-8f33-3c1bffc55540",
        "name": "Margherita Pizza",
        "created_at": "2023-08-04T04:23:12.366Z",
        "updated_at": "2023-08-04T03:13:33.041Z",
        "restaurant_id": "main_entity_pk"
      },
      {
        "id": "9cc4b74b-b6c0-4484-aadd-f7c876d6e50a",
        "name": "Chicken Alfredo Pasta",
        "created_at": "2023-08-04T01:12:27.753Z",
        "updated_at": "2023-08-03T19:17:55.935Z",
        "restaurant_id": "main_entity_pk"
      },
      {
        "id": "980c0f4b-82a3-4cf8-9eda-65b0c6438ef1",
        "name": "Beef Burger",
        "created_at": "2023-08-04T05:25:29.478Z",
        "updated_at": "2023-08-03T12:43:35.275Z",
        "restaurant_id": "main_entity_pk"
      },
      {
        "id": "ad9bd484-1f4b-4776-8d33-e010f309ffe4",
        "name": "Vegetable Stir-Fry",
        "created_at": "2023-08-04T03:57:49.638Z",
        "updated_at": "2023-08-03T19:35:35.724Z",
        "restaurant_id": "main_entity_pk"
      }
    ]
  },
  {
    "reservation": [
      {
        "id": "c6fdd761-24d6-445a-b0c9-0407a1aacdd2",
        "table_number": 77330,
        "reservation_time": "2023-08-03T16:51:59.189Z",
        "created_at": "2023-08-04T11:40:16.875Z",
        "updated_at": "2023-08-03T12:40:52.766Z",
        "guest_id": "user_entity_pk",
        "restaurant_id": "main_entity_pk"
      },
      {
        "id": "94c6164e-0a08-48a2-ba78-761b50006e1d",
        "table_number": 24184,
        "reservation_time": "2023-08-03T22:16:26.305Z",
        "created_at": "2023-08-04T01:21:10.223Z",
        "updated_at": "2023-08-03T16:09:13.887Z",
        "guest_id": "user_entity_pk",
        "restaurant_id": "main_entity_pk"
      },
      {
        "id": "3ddfa45a-17fe-4adb-afb5-0e1d6605580c",
        "table_number": 82360,
        "reservation_time": "2023-08-03T13:06:12.917Z",
        "created_at": "2023-08-04T05:07:50.733Z",
        "updated_at": "2023-08-04T07:29:45.685Z",
        "guest_id": "user_entity_pk",
        "restaurant_id": "main_entity_pk"
      },
      {
        "id": "a9c02cc1-5a56-4c13-866a-d1eba9e74030",
        "table_number": 61738,
        "reservation_time": "2023-08-03T20:10:05.826Z",
        "created_at": "2023-08-03T22:01:33.257Z",
        "updated_at": "2023-08-04T08:04:22.144Z",
        "guest_id": "user_entity_pk",
        "restaurant_id": "main_entity_pk"
      },
      {
        "id": "fd74d1c5-45d8-4bd8-889a-2f36c436ca79",
        "table_number": 65182,
        "reservation_time": "2023-08-03T21:57:18.791Z",
        "created_at": "2023-08-03T21:20:34.939Z",
        "updated_at": "2023-08-04T02:50:39.953Z",
        "guest_id": "user_entity_pk",
        "restaurant_id": "main_entity_pk"
      }
    ],
    "menu": [
      {
        "id": "7380cf08-83dc-4e05-a2e8-c830b5ec6a77",
        "name": "Breakfast Specials",
        "created_at": "2023-08-03T20:14:05.617Z",
        "updated_at": "2023-08-03T18:44:02.015Z",
        "restaurant_id": "main_entity_pk"
      },
      {
        "id": "1006dd5e-ba73-4840-bea1-65538f7fe77f",
        "name": "Lunch Combos",
        "created_at": "2023-08-04T10:37:49.858Z",
        "updated_at": "2023-08-03T19:37:31.363Z",
        "restaurant_id": "main_entity_pk"
      },
      {
        "id": "bf6d0eae-59ad-482a-8af5-e5a2e7c5bf7b",
        "name": "Dinner Entrees",
        "created_at": "2023-08-04T07:35:18.420Z",
        "updated_at": "2023-08-03T18:06:54.847Z",
        "restaurant_id": "main_entity_pk"
      },
      {
        "id": "c9c71395-682c-4d4e-a22c-804f418c5b5a",
        "name": "Vegetarian Options",
        "created_at": "2023-08-03T18:53:37.756Z",
        "updated_at": "2023-08-04T01:32:18.169Z",
        "restaurant_id": "main_entity_pk"
      },
      {
        "id": "0d2622a3-6011-4a95-b16c-ad4547327c24",
        "name": "Dessert Selections",
        "created_at": "2023-08-04T01:12:03.628Z",
        "updated_at": "2023-08-04T09:30:05.828Z",
        "restaurant_id": "main_entity_pk"
      }
    ]
  },
  {
    "reservation": [
      {
        "id": "8cc3aa3e-351a-4315-907e-1d9b023c4a49",
        "table_number": 58092,
        "reservation_time": "2023-08-03T15:37:52.335Z",
        "created_at": "2023-08-03T20:06:52.257Z",
        "updated_at": "2023-08-04T09:19:53.679Z",
        "guest_id": "user_entity_pk",
        "restaurant_id": "main_entity_pk"
      },
      {
        "id": "d1e70e63-3f0c-4385-8412-1c85a7581422",
        "table_number": 25567,
        "reservation_time": "2023-08-03T17:39:10.786Z",
        "created_at": "2023-08-04T11:29:28.386Z",
        "updated_at": "2023-08-04T09:05:03.336Z",
        "guest_id": "user_entity_pk",
        "restaurant_id": "main_entity_pk"
      },
      {
        "id": "fbcd2448-8c60-47f9-8904-77fa052400d6",
        "table_number": 31602,
        "reservation_time": "2023-08-03T18:54:25.203Z",
        "created_at": "2023-08-04T05:23:09.736Z",
        "updated_at": "2023-08-03T23:56:49.237Z",
        "guest_id": "user_entity_pk",
        "restaurant_id": "main_entity_pk"
      },
      {
        "id": "e6fe6a17-1bbf-4305-9155-6fe1919ae44b",
        "table_number": 73994,
        "reservation_time": "2023-08-03T17:57:36.771Z",
        "created_at": "2023-08-03T22:35:29.609Z",
        "updated_at": "2023-08-04T09:40:53.081Z",
        "guest_id": "user_entity_pk",
        "restaurant_id": "main_entity_pk"
      },
      {
        "id": "82de0b53-e703-4d79-a9be-2f241b8a1ff6",
        "table_number": 60423,
        "reservation_time": "2023-08-04T11:36:02.343Z",
        "created_at": "2023-08-03T14:28:22.808Z",
        "updated_at": "2023-08-04T09:18:13.593Z",
        "guest_id": "user_entity_pk",
        "restaurant_id": "main_entity_pk"
      }
    ],
    "menu": [
      {
        "id": "5e44c647-4f90-47c2-abd1-5a92e95f60bd",
        "name": "Breakfast Specials",
        "created_at": "2023-08-04T05:53:44.311Z",
        "updated_at": "2023-08-03T14:19:54.082Z",
        "restaurant_id": "main_entity_pk"
      },
      {
        "id": "143fd6ca-9df3-4e87-9025-ba600461bd70",
        "name": "Lunch Combos",
        "created_at": "2023-08-03T12:48:25.151Z",
        "updated_at": "2023-08-04T06:24:40.247Z",
        "restaurant_id": "main_entity_pk"
      },
      {
        "id": "277b35fd-ffb4-4376-9a8f-e8d17aec45df",
        "name": "Dinner Delights",
        "created_at": "2023-08-03T13:46:00.273Z",
        "updated_at": "2023-08-04T08:43:17.653Z",
        "restaurant_id": "main_entity_pk"
      },
      {
        "id": "75233761-e547-47ae-8752-b52557d7f20d",
        "name": "Vegetarian Options",
        "created_at": "2023-08-04T05:26:24.188Z",
        "updated_at": "2023-08-04T10:22:26.932Z",
        "restaurant_id": "main_entity_pk"
      },
      {
        "id": "20c97d5b-4f59-4f78-8ebb-460535eebabc",
        "name": "Chef's Recommendations",
        "created_at": "2023-08-04T00:18:52.600Z",
        "updated_at": "2023-08-04T04:24:01.721Z",
        "restaurant_id": "main_entity_pk"
      }
    ]
  },
  {
    "reservation": [
      {
        "id": "02550f86-6cca-4c10-8fca-5d984cdadf71",
        "table_number": 11613,
        "reservation_time": "2023-08-03T21:44:37.541Z",
        "created_at": "2023-08-03T15:44:56.346Z",
        "updated_at": "2023-08-03T14:19:09.664Z",
        "guest_id": "user_entity_pk",
        "restaurant_id": "main_entity_pk"
      },
      {
        "id": "810880f5-22b4-45db-8336-c4e84572aa58",
        "table_number": 36776,
        "reservation_time": "2023-08-03T18:48:35.982Z",
        "created_at": "2023-08-04T01:04:11.585Z",
        "updated_at": "2023-08-03T12:49:21.240Z",
        "guest_id": "user_entity_pk",
        "restaurant_id": "main_entity_pk"
      },
      {
        "id": "4436ac4a-3150-48ae-8b4a-2ef0ff23808a",
        "table_number": 99742,
        "reservation_time": "2023-08-04T09:18:14.158Z",
        "created_at": "2023-08-04T04:02:19.353Z",
        "updated_at": "2023-08-03T14:23:05.358Z",
        "guest_id": "user_entity_pk",
        "restaurant_id": "main_entity_pk"
      },
      {
        "id": "5f9f5911-c590-4bf5-ac23-a861e336b15a",
        "table_number": 23565,
        "reservation_time": "2023-08-03T21:05:53.289Z",
        "created_at": "2023-08-04T01:43:57.981Z",
        "updated_at": "2023-08-04T03:20:57.193Z",
        "guest_id": "user_entity_pk",
        "restaurant_id": "main_entity_pk"
      },
      {
        "id": "193cc0a0-6ddb-4ac3-9682-5d059138cc4e",
        "table_number": 87416,
        "reservation_time": "2023-08-04T07:42:04.115Z",
        "created_at": "2023-08-03T20:12:54.841Z",
        "updated_at": "2023-08-03T22:22:14.488Z",
        "guest_id": "user_entity_pk",
        "restaurant_id": "main_entity_pk"
      }
    ],
    "menu": [
      {
        "id": "5dffe3cd-a4ca-4171-b5f1-cbc4645d465e",
        "name": "Breakfast Specials",
        "created_at": "2023-08-03T22:47:38.230Z",
        "updated_at": "2023-08-03T20:45:00.912Z",
        "restaurant_id": "main_entity_pk"
      },
      {
        "id": "49736561-6a99-48d7-b7ad-fab779fff5d9",
        "name": "Lunch Combos",
        "created_at": "2023-08-03T14:08:18.969Z",
        "updated_at": "2023-08-04T04:06:59.908Z",
        "restaurant_id": "main_entity_pk"
      },
      {
        "id": "9778468f-929a-4cfb-b826-2084e22eddfc",
        "name": "Dinner Entrees",
        "created_at": "2023-08-03T18:40:27.299Z",
        "updated_at": "2023-08-03T21:29:34.040Z",
        "restaurant_id": "main_entity_pk"
      },
      {
        "id": "6a8ad6f1-e93e-4a04-b08d-e22f62f28473",
        "name": "Vegetarian Options",
        "created_at": "2023-08-04T11:29:41.529Z",
        "updated_at": "2023-08-04T01:15:18.167Z",
        "restaurant_id": "main_entity_pk"
      },
      {
        "id": "14593d87-70af-42fb-88bc-717bba56c8b4",
        "name": "Dessert Selections",
        "created_at": "2023-08-04T09:01:16.449Z",
        "updated_at": "2023-08-04T10:16:42.146Z",
        "restaurant_id": "main_entity_pk"
      }
    ]
  },
  {
    "reservation": [
      {
        "id": "75665b4a-ceb0-49ba-a320-39c4b7a8ca3f",
        "table_number": 26958,
        "reservation_time": "2023-08-03T14:16:49.824Z",
        "created_at": "2023-08-03T23:32:20.426Z",
        "updated_at": "2023-08-04T07:12:46.289Z",
        "guest_id": "user_entity_pk",
        "restaurant_id": "main_entity_pk"
      },
      {
        "id": "534d35a5-e98f-4c6f-b5ed-5411a3268cf5",
        "table_number": 43678,
        "reservation_time": "2023-08-03T14:50:50.666Z",
        "created_at": "2023-08-03T21:40:57.961Z",
        "updated_at": "2023-08-04T11:22:58.811Z",
        "guest_id": "user_entity_pk",
        "restaurant_id": "main_entity_pk"
      },
      {
        "id": "82888726-81f7-428b-a1fa-58ea10e66018",
        "table_number": 63682,
        "reservation_time": "2023-08-03T22:06:53.771Z",
        "created_at": "2023-08-04T11:45:35.320Z",
        "updated_at": "2023-08-03T18:03:58.405Z",
        "guest_id": "user_entity_pk",
        "restaurant_id": "main_entity_pk"
      },
      {
        "id": "7b0111f1-7735-46c5-b575-d6b36bd8ff49",
        "table_number": 8286,
        "reservation_time": "2023-08-04T10:02:14.208Z",
        "created_at": "2023-08-04T07:16:00.347Z",
        "updated_at": "2023-08-04T09:51:48.799Z",
        "guest_id": "user_entity_pk",
        "restaurant_id": "main_entity_pk"
      },
      {
        "id": "9c21d6e0-b3ac-4591-8260-de5cec1d5ca0",
        "table_number": 33171,
        "reservation_time": "2023-08-04T09:22:10.582Z",
        "created_at": "2023-08-03T17:41:15.916Z",
        "updated_at": "2023-08-04T06:26:09.424Z",
        "guest_id": "user_entity_pk",
        "restaurant_id": "main_entity_pk"
      }
    ],
    "menu": [
      {
        "id": "8a8d3b8b-cc34-44d7-93c9-5b3f38600ea6",
        "name": "Breakfast Specials",
        "created_at": "2023-08-04T08:11:33.905Z",
        "updated_at": "2023-08-04T12:10:07.318Z",
        "restaurant_id": "main_entity_pk"
      },
      {
        "id": "4d96c4ae-320e-4fd8-846d-897dffb88124",
        "name": "Lunch Combos",
        "created_at": "2023-08-04T07:03:34.757Z",
        "updated_at": "2023-08-04T12:24:35.385Z",
        "restaurant_id": "main_entity_pk"
      },
      {
        "id": "89418e10-ac5f-4a8f-93e8-862bbd3982fb",
        "name": "Dinner Entrees",
        "created_at": "2023-08-04T02:06:03.748Z",
        "updated_at": "2023-08-04T08:29:27.155Z",
        "restaurant_id": "main_entity_pk"
      },
      {
        "id": "4e4a56e1-22a0-44cd-bce9-615b2c763cd2",
        "name": "Vegetarian Options",
        "created_at": "2023-08-03T22:33:57.745Z",
        "updated_at": "2023-08-04T07:12:02.908Z",
        "restaurant_id": "main_entity_pk"
      },
      {
        "id": "60efcf64-22c4-41ca-abfe-8077eaabebaf",
        "name": "Dessert Selections",
        "created_at": "2023-08-03T23:34:19.008Z",
        "updated_at": "2023-08-04T12:18:40.890Z",
        "restaurant_id": "main_entity_pk"
      }
    ]
  },
  {
    "reservation": [
      {
        "id": "be46841f-d955-4706-b9c9-4c607c734367",
        "table_number": 7482,
        "reservation_time": "2023-08-04T07:27:35.163Z",
        "created_at": "2023-08-04T01:23:10.083Z",
        "updated_at": "2023-08-03T13:10:21.122Z",
        "guest_id": "user_entity_pk",
        "restaurant_id": "main_entity_pk"
      },
      {
        "id": "146b8704-ab04-4684-a00d-9bef6976e769",
        "table_number": 45801,
        "reservation_time": "2023-08-03T18:03:04.120Z",
        "created_at": "2023-08-03T14:15:08.279Z",
        "updated_at": "2023-08-04T07:31:38.698Z",
        "guest_id": "user_entity_pk",
        "restaurant_id": "main_entity_pk"
      },
      {
        "id": "77c47a59-9602-4dda-98ed-e845f61307de",
        "table_number": 93944,
        "reservation_time": "2023-08-04T11:54:20.945Z",
        "created_at": "2023-08-04T06:56:06.024Z",
        "updated_at": "2023-08-03T16:05:34.375Z",
        "guest_id": "user_entity_pk",
        "restaurant_id": "main_entity_pk"
      },
      {
        "id": "d73be3ee-12d4-41c7-a4b6-1e237784b541",
        "table_number": 42026,
        "reservation_time": "2023-08-04T03:59:22.311Z",
        "created_at": "2023-08-04T10:16:27.928Z",
        "updated_at": "2023-08-04T04:34:58.834Z",
        "guest_id": "user_entity_pk",
        "restaurant_id": "main_entity_pk"
      },
      {
        "id": "ee75bb63-144a-4b19-be0b-773a090e5401",
        "table_number": 10293,
        "reservation_time": "2023-08-04T01:04:40.845Z",
        "created_at": "2023-08-03T14:20:49.334Z",
        "updated_at": "2023-08-03T19:19:09.645Z",
        "guest_id": "user_entity_pk",
        "restaurant_id": "main_entity_pk"
      }
    ],
    "menu": [
      {
        "id": "d29672c6-d8bc-4297-9609-9afc2942e210",
        "name": "Breakfast Specials",
        "created_at": "2023-08-04T12:14:26.496Z",
        "updated_at": "2023-08-03T16:31:42.572Z",
        "restaurant_id": "main_entity_pk"
      },
      {
        "id": "2d639cfc-f72c-4ca0-8938-374166ddf4b7",
        "name": "Lunch Combos",
        "created_at": "2023-08-04T02:50:51.853Z",
        "updated_at": "2023-08-03T14:17:29.128Z",
        "restaurant_id": "main_entity_pk"
      },
      {
        "id": "d51a3fc7-34cf-4bae-ad91-fa6562d3def2",
        "name": "Dinner Entrees",
        "created_at": "2023-08-03T17:34:16.325Z",
        "updated_at": "2023-08-04T07:58:42.545Z",
        "restaurant_id": "main_entity_pk"
      },
      {
        "id": "5c7244e3-676b-49e5-b1cb-6037edb4e042",
        "name": "Dessert Selections",
        "created_at": "2023-08-04T01:15:50.851Z",
        "updated_at": "2023-08-04T00:04:10.073Z",
        "restaurant_id": "main_entity_pk"
      },
      {
        "id": "ecf18e34-362a-40a1-b88d-036904b27e87",
        "name": "Beverage Options",
        "created_at": "2023-08-04T07:41:50.604Z",
        "updated_at": "2023-08-03T22:38:52.145Z",
        "restaurant_id": "main_entity_pk"
      }
    ]
  },
  {
    "reservation": [
      {
        "id": "9c91f10a-2f51-40a8-a5c7-c35342ffb4a5",
        "table_number": 51224,
        "reservation_time": "2023-08-03T20:13:05.811Z",
        "created_at": "2023-08-03T16:48:18.458Z",
        "updated_at": "2023-08-04T07:04:31.662Z",
        "guest_id": "user_entity_pk",
        "restaurant_id": "main_entity_pk"
      },
      {
        "id": "6f5de51a-48df-48e4-a7c6-d6f6753ddb2e",
        "table_number": 13341,
        "reservation_time": "2023-08-03T20:38:18.894Z",
        "created_at": "2023-08-04T11:33:27.089Z",
        "updated_at": "2023-08-03T14:34:21.528Z",
        "guest_id": "user_entity_pk",
        "restaurant_id": "main_entity_pk"
      },
      {
        "id": "c1fdecfc-ddfd-4ed2-aeab-7e1e20729614",
        "table_number": 63475,
        "reservation_time": "2023-08-04T05:54:17.321Z",
        "created_at": "2023-08-04T10:53:49.763Z",
        "updated_at": "2023-08-03T12:46:33.710Z",
        "guest_id": "user_entity_pk",
        "restaurant_id": "main_entity_pk"
      },
      {
        "id": "9a1c0487-0d21-446f-b19e-8e4a7c80b040",
        "table_number": 30031,
        "reservation_time": "2023-08-04T08:04:21.924Z",
        "created_at": "2023-08-04T05:11:09.253Z",
        "updated_at": "2023-08-04T09:34:11.173Z",
        "guest_id": "user_entity_pk",
        "restaurant_id": "main_entity_pk"
      },
      {
        "id": "9d6832a9-f963-4afc-8751-20a27e3e910a",
        "table_number": 12313,
        "reservation_time": "2023-08-03T23:35:48.415Z",
        "created_at": "2023-08-03T21:23:34.901Z",
        "updated_at": "2023-08-03T21:11:48.444Z",
        "guest_id": "user_entity_pk",
        "restaurant_id": "main_entity_pk"
      }
    ],
    "menu": [
      {
        "id": "d990171e-ec18-46df-bf05-e646e83986e8",
        "name": "Breakfast Specials",
        "created_at": "2023-08-03T17:55:32.467Z",
        "updated_at": "2023-08-03T17:22:11.820Z",
        "restaurant_id": "main_entity_pk"
      },
      {
        "id": "33c3d8d1-0bb4-4681-872e-ab45f9435309",
        "name": "Lunch Combos",
        "created_at": "2023-08-04T07:47:48.856Z",
        "updated_at": "2023-08-04T01:20:48.513Z",
        "restaurant_id": "main_entity_pk"
      },
      {
        "id": "34caf66b-ea93-47bc-a4c0-6e24a431eab0",
        "name": "Dinner Delights",
        "created_at": "2023-08-03T12:45:01.126Z",
        "updated_at": "2023-08-03T12:53:16.141Z",
        "restaurant_id": "main_entity_pk"
      },
      {
        "id": "e09064f9-4874-4f78-8453-b88d7749b278",
        "name": "Vegetarian Options",
        "created_at": "2023-08-03T22:00:07.444Z",
        "updated_at": "2023-08-04T00:27:43.176Z",
        "restaurant_id": "main_entity_pk"
      },
      {
        "id": "f70b9e4f-2f61-4105-987b-f02436a1c350",
        "name": "Chef's Recommendations",
        "created_at": "2023-08-04T05:53:25.092Z",
        "updated_at": "2023-08-04T09:41:12.812Z",
        "restaurant_id": "main_entity_pk"
      }
    ]
  },
  {
    "reservation": [
      {
        "id": "eeb94195-83d5-4328-aaca-11c9ae2b912f",
        "table_number": 761,
        "reservation_time": "2023-08-04T03:42:20.787Z",
        "created_at": "2023-08-04T02:12:21.407Z",
        "updated_at": "2023-08-04T06:04:22.619Z",
        "guest_id": "user_entity_pk",
        "restaurant_id": "main_entity_pk"
      },
      {
        "id": "a6475f09-97a7-4da1-83d3-3bc00c8fcb53",
        "table_number": 6363,
        "reservation_time": "2023-08-04T08:00:43.457Z",
        "created_at": "2023-08-04T06:43:20.700Z",
        "updated_at": "2023-08-03T14:18:19.732Z",
        "guest_id": "user_entity_pk",
        "restaurant_id": "main_entity_pk"
      },
      {
        "id": "febaf356-8bad-4e00-87eb-c63cb848fa7e",
        "table_number": 54155,
        "reservation_time": "2023-08-04T03:03:09.489Z",
        "created_at": "2023-08-04T02:17:05.014Z",
        "updated_at": "2023-08-03T17:10:08.756Z",
        "guest_id": "user_entity_pk",
        "restaurant_id": "main_entity_pk"
      },
      {
        "id": "a9438526-b9ac-4936-9604-759877425e6d",
        "table_number": 49398,
        "reservation_time": "2023-08-04T03:56:19.993Z",
        "created_at": "2023-08-03T22:11:35.037Z",
        "updated_at": "2023-08-03T21:23:27.700Z",
        "guest_id": "user_entity_pk",
        "restaurant_id": "main_entity_pk"
      },
      {
        "id": "df16f049-1ec1-4817-af9c-2507940f8fda",
        "table_number": 81299,
        "reservation_time": "2023-08-04T11:13:20.962Z",
        "created_at": "2023-08-03T22:04:01.634Z",
        "updated_at": "2023-08-04T02:08:48.226Z",
        "guest_id": "user_entity_pk",
        "restaurant_id": "main_entity_pk"
      }
    ],
    "menu": [
      {
        "id": "a4b8317a-e8bf-4f94-b63e-baff61a720d8",
        "name": "Breakfast Specials",
        "created_at": "2023-08-03T16:44:58.687Z",
        "updated_at": "2023-08-03T19:59:04.449Z",
        "restaurant_id": "main_entity_pk"
      },
      {
        "id": "c43770c1-c47c-4b5e-b254-fcedc5832460",
        "name": "Lunch Combos",
        "created_at": "2023-08-03T17:34:49.675Z",
        "updated_at": "2023-08-03T15:18:22.784Z",
        "restaurant_id": "main_entity_pk"
      },
      {
        "id": "34930ac2-ff41-40ef-9c6c-0a66b71244e2",
        "name": "Dinner Entrees",
        "created_at": "2023-08-04T01:18:24.935Z",
        "updated_at": "2023-08-04T10:14:18.863Z",
        "restaurant_id": "main_entity_pk"
      },
      {
        "id": "30d89cce-4e13-499b-a7b1-8e0899c55127",
        "name": "Vegetarian Options",
        "created_at": "2023-08-04T07:40:11.154Z",
        "updated_at": "2023-08-04T04:42:39.782Z",
        "restaurant_id": "main_entity_pk"
      },
      {
        "id": "e06a415c-5240-4ff4-a655-ce7f6932bf88",
        "name": "Dessert Delights",
        "created_at": "2023-08-03T12:45:11.842Z",
        "updated_at": "2023-08-03T23:12:23.240Z",
        "restaurant_id": "main_entity_pk"
      }
    ]
  }
]
